flattenator/__init__.py
flattenator/_version.py
flattenator/flattenator.py
flattenator-0.0.2.dist-info/LICENSE
flattenator-0.0.2.dist-info/METADATA
flattenator-0.0.2.dist-info/WHEEL
flattenator-0.0.2.dist-info/entry_points.txt
flattenator-0.0.2.dist-info/top_level.txt
flattenator-0.0.2.dist-info/RECORD
